resume_builder/__init__.py
resume_builder/pdf_converter.py
resume_builder/resume.py
resume_maker/__init__.py
resume_maker/pdf_converter.py
resume_maker/resume.py
resume_maker-0.1.0.dist-info/METADATA
resume_maker-0.1.0.dist-info/WHEEL
resume_maker-0.1.0.dist-info/top_level.txt
resume_maker-0.1.0.dist-info/RECORD
