Metadata-Version: 2.1
Name: resume-maker
Version: 0.1.0
Summary: Resume maker from json file
Home-page: https://github.com/MehmetUzel
Author: Mehmet Uzel
Author-email: 98mehmetuzel@gmail.com
License: MIT
Keywords: resume,maker,builder,cv,json
Platform: UNKNOWN
Classifier: Intended Audience :: Developers
Classifier: License :: OSI Approved :: MIT License
Classifier: Programming Language :: Python
Classifier: Programming Language :: Python :: 3.7
Classifier: Programming Language :: Python :: 3.8
Classifier: Programming Language :: Python :: 3.9
Classifier: Operating System :: OS Independent
Requires-Dist: Pillow (==9.4.0)
Requires-Dist: pydantic (==1.10.4)
Requires-Dist: reportlab (==3.6.12)
Requires-Dist: typing-extensions (==4.4.0)
